monarchtominttoreport/__init__.py
monarchtominttoreport/_version.py
monarchtominttoreport/convert.py
monarchtominttoreport-0.1.dist-info/LICENSE
monarchtominttoreport-0.1.dist-info/METADATA
monarchtominttoreport-0.1.dist-info/WHEEL
monarchtominttoreport-0.1.dist-info/entry_points.txt
monarchtominttoreport-0.1.dist-info/top_level.txt
monarchtominttoreport-0.1.dist-info/RECORD
