Metadata-Version: 2.2
Name: monarchtominttoreport
Version: 0.1
Summary: Convert a Monarch CSV transaction export file to legacy Mint format, suitable for MintToReport
Maintainer-email: Micah Wengren <micah.wengren@gmail.com>
License: Copyright 2025 Micah Wengren
Project-URL: documentation, https://github.com/mwengren/monarchtominttoreport
Project-URL: homepage, https://github.com/mwengren/monarchtominttoreport
Project-URL: repository, https://github.com/mwengren/monarchtominttoreport
Classifier: Programming Language :: Python :: 3 :: Only
Classifier: Programming Language :: Python :: 3.8
Classifier: Programming Language :: Python :: 3.9
Classifier: Programming Language :: Python :: 3.10
Classifier: Programming Language :: Python :: 3.11
Classifier: Programming Language :: Python :: 3.12
Requires-Python: >=3.8
License-File: LICENSE
Requires-Dist: polars
